mcp_llm/__init__.py
mcp_llm/main.py
mcp_client_llm-0.1.0.dist-info/METADATA
mcp_client_llm-0.1.0.dist-info/WHEEL
mcp_client_llm-0.1.0.dist-info/entry_points.txt
mcp_client_llm-0.1.0.dist-info/RECORD
