Metadata-Version: 2.1
Name: mcp-client-llm
Version: 0.1.0
Summary: MCP server for the LLMs
License: Apache-2.0
Author: Kacper Łukawski
Author-email: lukawski.kacper@gmail.com
Requires-Python: >=3.10,<4.0
Classifier: License :: OSI Approved :: Apache Software License
Classifier: Programming Language :: Python :: 3
Classifier: Programming Language :: Python :: 3.10
Classifier: Programming Language :: Python :: 3.11
Classifier: Programming Language :: Python :: 3.12
